pydicates/__init__.py
pydicates/contexts.py
pydicates/exceptions.py
pydicates/operations.py
pydicates/predicates.py
pydicates-0.1.1.dist-info/LICENSE
pydicates-0.1.1.dist-info/WHEEL
pydicates-0.1.1.dist-info/METADATA
pydicates-0.1.1.dist-info/RECORD
