Metadata-Version: 2.1
Name: pydicates
Version: 0.1.1
Summary: Predicates for Python.
Home-page: https://github.com/Tiendil/pydicates
License: BSD-3-Clause
Keywords: predicates,functional,
Author: Aliaksei Yaletski (Tiendil)
Author-email: a.eletsky@gmail.com
Requires-Python: >=3.6,<4.0
Classifier: Intended Audience :: Developers
Classifier: License :: OSI Approved :: BSD License
Classifier: Natural Language :: English
Classifier: Programming Language :: Python :: 3
Classifier: Programming Language :: Python :: 3.6
Classifier: Programming Language :: Python :: 3.7
Classifier: Programming Language :: Python :: 3.8
Classifier: Programming Language :: Python :: 3.9
Classifier: Topic :: Software Development
Classifier: Topic :: Software Development :: Libraries
Classifier: Topic :: Software Development :: Libraries :: Python Modules
Project-URL: Repository, https://github.com/Tiendil/pydicates
